libint2/__init__.py
libint2/libint2.cpython-312-x86_64-linux-gnu.so
libint2/share/libint/basis/3-21g.g94
libint2/share/libint/basis/6-311g**.g94
libint2/share/libint/basis/6-311gss.g94
libint2/share/libint/basis/6-31g**.g94
libint2/share/libint/basis/6-31g*.g94
libint2/share/libint/basis/6-31g.g94
libint2/share/libint/basis/6-31gs.g94
libint2/share/libint/basis/6-31gss.g94
libint2/share/libint/basis/ano-rcc-mb.g94
libint2/share/libint/basis/ano-rcc.g94
libint2/share/libint/basis/aug-cc-pv5z-cabs.g94
libint2/share/libint/basis/aug-cc-pvdz-cabs.g94
libint2/share/libint/basis/aug-cc-pvqz-cabs.g94
libint2/share/libint/basis/aug-cc-pvtz-cabs.g94
libint2/share/libint/basis/augmentation-cc-pv5z-jkfit.g94
libint2/share/libint/basis/augmentation-cc-pv5z-ri.g94
libint2/share/libint/basis/augmentation-cc-pv5z.g94
libint2/share/libint/basis/augmentation-cc-pv6z-ri.g94
libint2/share/libint/basis/augmentation-cc-pv6z.g94
libint2/share/libint/basis/augmentation-cc-pv7z.g94
libint2/share/libint/basis/augmentation-cc-pvdz-jkfit.g94
libint2/share/libint/basis/augmentation-cc-pvdz-ri.g94
libint2/share/libint/basis/augmentation-cc-pvdz.g94
libint2/share/libint/basis/augmentation-cc-pvqz-jkfit.g94
libint2/share/libint/basis/augmentation-cc-pvqz-ri.g94
libint2/share/libint/basis/augmentation-cc-pvqz.g94
libint2/share/libint/basis/augmentation-cc-pvtz-jkfit.g94
libint2/share/libint/basis/augmentation-cc-pvtz-ri.g94
libint2/share/libint/basis/augmentation-cc-pvtz.g94
libint2/share/libint/basis/cc-pv5z-jkfit.g94
libint2/share/libint/basis/cc-pv5z-ri.g94
libint2/share/libint/basis/cc-pv5z.g94
libint2/share/libint/basis/cc-pv6z-ri.g94
libint2/share/libint/basis/cc-pv6z.g94
libint2/share/libint/basis/cc-pv7z.g94
libint2/share/libint/basis/cc-pvdz-f12-cabs.g94
libint2/share/libint/basis/cc-pvdz-f12.g94
libint2/share/libint/basis/cc-pvdz-jkfit.g94
libint2/share/libint/basis/cc-pvdz-ri.g94
libint2/share/libint/basis/cc-pvdz.g94
libint2-2.12.0.dist-info/METADATA
libint2-2.12.0.dist-info/WHEEL
libint2-2.12.0.dist-info/RECORD
