Metadata-Version: 2.2
Name: libint2
Version: 2.12.0
Summary: Python bindings for the Libint library - a high-performance library for computing molecular integrals
Author: Libint Contributors
License: LGPL-3.0-or-later
Classifier: Development Status :: 5 - Production/Stable
Classifier: Intended Audience :: Science/Research
Classifier: License :: OSI Approved :: GNU Lesser General Public License v3 or later (LGPLv3+)
Classifier: Programming Language :: C++
Classifier: Programming Language :: Python :: 3
Classifier: Programming Language :: Python :: 3.8
Classifier: Programming Language :: Python :: 3.9
Classifier: Programming Language :: Python :: 3.10
Classifier: Programming Language :: Python :: 3.11
Classifier: Programming Language :: Python :: 3.12
Classifier: Topic :: Scientific/Engineering :: Chemistry
Requires-Python: >=3.8
Requires-Dist: numpy<2.4,>=2.0
